{
  "name": "teams/XK4APZzH5Iz2CwBKTFfO/Screenshot from 2022-09-02 12-30-34.png",
  "bucket": "sigh-f656a.appspot.com",
  "metageneration": 1,
  "generation": 1662364800634,
  "contentType": "image/png",
  "storageClass": "STANDARD",
  "contentDisposition": "inline",
  "customMetadata": {},
  "downloadTokens": [
    "a403511e-dcbd-4fa6-88d4-cee8e01158f9"
  ],
  "etag": "sIJii+kDZjp0g4B+elhm1PeY5GE",
  "timeCreated": "2022-09-05T08:00:00.634Z",
  "updated": "2022-09-05T08:00:00.634Z",
  "size": 64874,
  "md5Hash": "j8tXIJz48JPlK7gFI2yXZQ==",
  "crc32c": "2208162314"
}